negate/__init__.py
negate/negate.py
negate/py.typed
negate/tokens.py
negate/version.py
negate-1.1.6.dist-info/METADATA
negate-1.1.6.dist-info/WHEEL
negate-1.1.6.dist-info/licenses/LICENSE
negate-1.1.6.dist-info/RECORD
