Metadata-Version: 2.3
Name: negate
Version: 1.1.6
Summary: A Python module that negates sentences.
Project-URL: Homepage, https://github.com/dmlls/negate
Project-URL: GitHub Issues, https://github.com/dmlls/negate/issues
Project-URL: GitHub Repo, https://github.com/dmlls/negate
Author-email: Diego Miguel Lozano <hello@diegomiguel.me>
Maintainer-email: Diego Miguel Lozano <hello@diegomiguel.me>
License: 
License-File: LICENSE
Keywords: NLP,negate,negation,negator,sentence-negation,sentence-negator
Classifier: Development Status :: 4 - Beta
Classifier: Intended Audience :: Science/Research
Classifier: License :: OSI Approved :: MIT License
Classifier: Natural Language :: English
Classifier: Operating System :: OS Independent
Classifier: Programming Language :: Python :: 3
Classifier: Programming Language :: Python :: 3.7
Classifier: Programming Language :: Python :: 3.8
Classifier: Programming Language :: Python :: 3.9
Classifier: Programming Language :: Python :: 3.10
Classifier: Programming Language :: Python :: 3.11
Classifier: Programming Language :: Python :: 3.12
Classifier: Topic :: Scientific/Engineering :: Artificial Intelligence
Requires-Python: >=3.7
Requires-Dist: lemminflect<0.3.0,>=0.2.3
Requires-Dist: spacy<3.9.0,>=3.8.0
Provides-Extra: transformers
Requires-Dist: spacy-transformers<1.5.0,>=1.3.5; extra == 'transformers'
